eltyer_investing_algorithm_framework/__init__.py
eltyer_investing_algorithm_framework/exceptions.py
eltyer_investing_algorithm_framework/configuration/__init__.py
eltyer_investing_algorithm_framework/configuration/constants.py
eltyer_investing_algorithm_framework/initializer/__init__.py
eltyer_investing_algorithm_framework/order_executor/__init__.py
eltyer_investing_algorithm_framework/portfolio_manager/__init__.py
eltyer_investing_algorithm_framework/setup/__init__.py
eltyer_investing_algorithm_framework/utils/__init__.py
eltyer_investing_algorithm_framework-0.5.4.dist-info/LICENSE
eltyer_investing_algorithm_framework-0.5.4.dist-info/METADATA
eltyer_investing_algorithm_framework-0.5.4.dist-info/WHEEL
eltyer_investing_algorithm_framework-0.5.4.dist-info/top_level.txt
eltyer_investing_algorithm_framework-0.5.4.dist-info/RECORD
