Metadata-Version: 2.1
Name: eltyer-investing-algorithm-framework
Version: 0.5.4
Summary: Official ELTYER plugin for the investing algorithm framework
Home-page: https://github.com/ELTYER/eltyer-investing-algorithm-framework.git
Author: ELTYER
License: Apache License 2.0
Keywords: ELTYER,eltyer,investing-algorithm,investing-algorithm-framework,INVESTING,BOT,ALGORITHM,FRAMEWORK,investing-bots,trading-bots
Classifier: Intended Audience :: Developers
Classifier: Programming Language :: Python :: 3
Classifier: Programming Language :: Python :: 3.4
Classifier: Programming Language :: Python :: 3.5
Classifier: Programming Language :: Python :: 3.6
Classifier: Topic :: Software Development
Classifier: License :: OSI Approved :: Apache Software License
Classifier: Operating System :: OS Independent
Requires-Python: >=3
License-File: LICENSE
Requires-Dist: investing-algorithm-framework (>=0.19.6)
Requires-Dist: eltyer (>=0.3.3)
